multicalc/__init__.py
multicalc/api.py
multicalc/cli.py
multicalc/core/__init__.py
multicalc/core/calculator.py
multicalc-1.0.0.dist-info/METADATA
multicalc-1.0.0.dist-info/WHEEL
multicalc-1.0.0.dist-info/entry_points.txt
multicalc-1.0.0.dist-info/licenses/LICENSE
multicalc-1.0.0.dist-info/RECORD
