Metadata-Version: 2.4
Name: multicalc
Version: 1.0.0
Summary: A modular Python calculator with reusable core logic, CLI, REST API, and import — demonstrating a multi-entry architecture.
Author-email: Matheus de Andrade <matheusdeandradesv@gmail.com>
License: MIT
License-File: LICENSE
Keywords: api,calculator,cli,example,fastapi,modular,python,typer
Classifier: Intended Audience :: Developers
Classifier: License :: OSI Approved :: MIT License
Classifier: Operating System :: OS Independent
Classifier: Programming Language :: Python :: 3
Classifier: Topic :: Software Development :: Libraries :: Python Modules
Classifier: Topic :: Utilities
Requires-Python: >=3.8
Requires-Dist: fastapi>=0.116
Requires-Dist: typer>=0.16
Requires-Dist: uvicorn[standard]>=0.35
Provides-Extra: all
Requires-Dist: fastapi>=0.116; extra == 'all'
Requires-Dist: typer>=0.16; extra == 'all'
Requires-Dist: uvicorn[standard]>=0.35; extra == 'all'
Provides-Extra: api
Requires-Dist: fastapi>=0.116; extra == 'api'
Requires-Dist: uvicorn[standard]>=0.35; extra == 'api'
Provides-Extra: cli
Requires-Dist: typer>=0.16; extra == 'cli'
